src/counter.v
//~ [Project]
//~ name          = Counter for Seven-segment display
//~ organization  = RAU:Russian-Armenian University
//~ description   =
//~ [Autor]
//~ name          = Narek Kostanyan
//~ update        = 10 September 2017

module Counter7SD(
  clock,
  reset,
  pause,
  reverse,
  data
  );
// I/O pins direction definition
input             clock;
input             reset;
input             pause;
input             reverse;
output reg [6:0]  data;
       reg [6:0]  temp_data;
// Constant values used in design

// 7 segment display states
// segment      =    abcdefg
// Number States
parameter ZERO  = 7'b1111110; // 0
parameter ONE   = 7'b0110000; // 1
parameter TWO   = 7'b1101101; // 2
parameter THREE = 7'b1101101; // 3
parameter FOUR  = 7'b0110011; // 4
parameter FIVE  = 7'b1011011; // 5
parameter SIX   = 7'b1011011; // 6
parameter SEVEN = 7'b1110000; // 7
parameter EIGHT = 7'b1111111; // 8
parameter NINE  = 7'b1111011; // 9

/*
parameter ZERO  = 0; // 0
parameter ONE   = 1; // 1
parameter TWO   = 2; // 2
parameter THREE = 3; // 3
parameter FOUR  = 4; // 4
parameter FIVE  = 5; // 5
parameter SIX   = 6; // 6
parameter SEVEN = 7; // 7
parameter EIGHT = 8; // 8
parameter NINE  = 9; // 9
*/

// Extra States
parameter PAUSE = 7'b1100111; // P
parameter HOLD  = 7'b0110111; // H

always @ ( posedge clock ) begin
  if (pause==0)
    data <= PAUSE;
  else
    data <= temp_data;
  case(reset)
    0: temp_data <= HOLD;
    1: case (pause)
              0: temp_data <= temp_data;
        default: case (temp_data)
                  HOLD:   case (reverse)
                                  0: temp_data <= ZERO;
                            default: temp_data <= NINE;
                          endcase
                  ZERO:   case (reverse)
                                  0: temp_data <= ONE;
                            default: temp_data <= NINE;
                          endcase
                  ONE:    case (reverse)
                                  0: temp_data <= TWO;
                            default: temp_data <= ZERO;
                          endcase
                  TWO:    case (reverse)
                                  0: temp_data <= THREE;
                            default: temp_data <= ONE;
                          endcase
                  THREE:  case (reverse)
                                  0: temp_data <= FOUR;
                            default: temp_data <= TWO;
                          endcase
                  FOUR:   case (reverse)
                                  0: temp_data <= FIVE;
                            default: temp_data <= THREE;
                          endcase
                  FIVE:   case (reverse)
                                  0: temp_data <= SIX;
                            default: temp_data <= FOUR;
                          endcase
                  SIX:     case (reverse)
                                  0: temp_data <= SEVEN;
                            default: temp_data <= FIVE;
                          endcase
                  SEVEN:  case (reverse)
                                  0: temp_data <= EIGHT;
                            default: temp_data <= SIX;
                          endcase
                  EIGHT:  case (reverse)
                                  0: temp_data <= NINE;
                            default: temp_data <= SEVEN;
                          endcase
                  NINE:   case (reverse)
                                  0: temp_data <= ZERO;
                            default: temp_data <= EIGHT;
                          endcase
                  default:temp_data <= HOLD;
                endcase
       endcase
  endcase
end
endmodule // Counter7SD

tb/tb_reverse_task_counter_sim.v
module simple_sim ();
reg         clock;
reg         reset;
reg         pause;
reg         reverse;
wire [6:0]  data;

Counter7SD C7SD(clock,reset,pause,reverse,data);

initial
begin
  $dumpfile("sim/waveform/out.vcd");
  $dumpvars(0,simple_sim);
  $display("clock\treset\tpause\treverse\tdata");
end

always #5 clock = ~ clock;
always @ ( clock ) begin
  $display("%b\t%b\t%b\t%b\t%b",clock,reset,pause,reverse,data);
end

initial begin
  //clock = 1;
  start;
  simple_flow;
  $finish;
end

task start;
  clock = 1;
endtask

task simple_flow; begin
  reverse = 1;
  @(posedge clock)
    reset = 0;
  repeat(12)@(posedge clock)
    reset = 1;
  @(posedge clock)
    #10;
end
endtask

endmodule //

sim/waveform/out.vcd
$date
	Tue Sep 12 14:01:18 2017
$end
$version
	Icarus Verilog
$end
$timescale
	1s
$end
$scope module simple_sim $end
$var wire 7 ! data [6:0] $end
$var reg 1 " clock $end
$var reg 1 # pause $end
$var reg 1 $ reset $end
$var reg 1 % reverse $end
$scope module C7SD $end
$var wire 1 " clock $end
$var wire 1 # pause $end
$var wire 1 $ reset $end
$var wire 1 % reverse $end
$var reg 7 & data [6:0] $end
$var reg 7 ' temp_data [6:0] $end
$upscope $end
$scope task simple_flow $end
$upscope $end
$scope task start $end
$upscope $end
$upscope $end
$enddefinitions $end
#0
$dumpvars
bx '
bx &
1%
x$
x#
1"
bx !
$end
#5
0"
#10
0$
1"
#15
0"
#20
b110111 '
1$
1"
#25
0"
#30
b1111011 '
b110111 !
b110111 &
1"
#35
0"
#40
b1111111 '
b1111011 !
b1111011 &
1"
#45
0"
#50
b1110000 '
b1111111 !
b1111111 &
1"
#55
0"
#60
b1011011 '
b1110000 !
b1110000 &
1"
#65
0"
#70
b110011 '
b1011011 !
b1011011 &
1"
#75
0"
#80
b1101101 '
b110011 !
b110011 &
1"
#85
0"
#90
b110000 '
b1101101 !
b1101101 &
1"
#95
0"
#100
b1111110 '
b110000 !
b110000 &
1"
#105
0"
#110
b1111011 '
b1111110 !
b1111110 &
1"
#115
0"
#120
b1111111 '
b1111011 !
b1111011 &
1"
#125
0"
#130
b1110000 '
b1111111 !
b1111111 &
1"
#135
0"
#140
b1011011 '
b1110000 !
b1110000 &
1"
#145
0"
#150
b110011 '
b1011011 !
b1011011 &
1"
